rt/__init__.py
rt/exceptions.py
rt/py.typed
rt/rest1.py
rt/rest2.py
rt-3.3.9.dist-info/METADATA
rt-3.3.9.dist-info/WHEEL
rt-3.3.9.dist-info/licenses/AUTHORS
rt-3.3.9.dist-info/licenses/LICENSE
rt-3.3.9.dist-info/RECORD
