Metadata-Version: 2.4
Name: rt
Version: 3.3.9
Summary: Python interface to Request Tracker API
Project-URL: Homepage, https://github.com/python-rt/python-rt
Project-URL: Documentation, https://python-rt.readthedocs.io/
Project-URL: Source, https://github.com/python-rt/python-rt
Project-URL: Tracker, https://github.com/python-rt/python-rt/issues
Project-URL: Changelog, https://github.com/python-rt/python-rt/blob/master/CHANGELOG.md
Author-email: Georges Toth <georges.toth@govcert.etat.lu>
License: GNU General Public License v3 (GPLv3)
License-File: AUTHORS
License-File: LICENSE
Classifier: Development Status :: 5 - Production/Stable
Classifier: Environment :: Console
Classifier: Intended Audience :: Developers
Classifier: License :: OSI Approved :: GNU General Public License v3 (GPLv3)
Classifier: Operating System :: POSIX
Classifier: Programming Language :: Python
Classifier: Programming Language :: Python :: 3
Classifier: Programming Language :: Python :: 3 :: Only
Classifier: Topic :: Software Development :: Libraries :: Python Modules
Requires-Python: >=3.9
Requires-Dist: httpx~=0.28
Requires-Dist: requests~=2.32
